SSS_Package/__init__.py
SSS_Package-2019.12.27.dist-info/LICENSE
SSS_Package-2019.12.27.dist-info/METADATA
SSS_Package-2019.12.27.dist-info/WHEEL
SSS_Package-2019.12.27.dist-info/top_level.txt
SSS_Package-2019.12.27.dist-info/RECORD
