Metadata-Version: 2.1
Name: SSS-Package
Version: 2019.12.27
Summary: Set of useful functions
Home-page: https://github.com/SergiiSerednii
Author: Sergii Serednii
Author-email: sseredniy@gmail.com
License: UNKNOWN
Platform: UNKNOWN
Classifier: Programming Language :: Python :: 3
Classifier: License :: OSI Approved :: MIT License
Classifier: Operating System :: OS Independent
Requires-Python: >=3.6
Requires-Dist: pandas (>=0.24.2)
Requires-Dist: numpy (>=1.16.4)
Requires-Dist: xgboost (>=0.90)
Requires-Dist: hyperopt (>=0.2.2)
Requires-Dist: psycopg2 (>=2.7.6.1)
